reloady/__init__.py
reloady/main.py
reloady/reloady.py
reloady-0.1.7.dist-info/LICENSE
reloady-0.1.7.dist-info/METADATA
reloady-0.1.7.dist-info/WHEEL
reloady-0.1.7.dist-info/entry_points.txt
reloady-0.1.7.dist-info/top_level.txt
reloady-0.1.7.dist-info/RECORD
