Metadata-Version: 2.1
Name: reloady
Version: 0.1.7
Summary: A tool for automatically reloading Python programs on file changes
Author-email: Moetaz <moetaz@pingoware.tech>
Project-URL: Homepage, https://github.com/makergeek/reloady
Project-URL: Bug Tracker, https://github.com/makergeek/reloady/issues
Classifier: Programming Language :: Python :: 3
Classifier: License :: OSI Approved :: MIT License
Classifier: Operating System :: OS Independent
Requires-Python: >=3.7
License-File: LICENSE
